python_9_42_poetry_app/__init__.py
python_9_42_poetry_app/people_manager/__init__.py
python_9_42_poetry_app/people_manager/app.py
python_9_42_poetry_app/people_manager/model.py
python_9_42_poetry_app_v2-0.1.0.dist-info/WHEEL
python_9_42_poetry_app_v2-0.1.0.dist-info/METADATA
python_9_42_poetry_app_v2-0.1.0.dist-info/RECORD
